testnexus/__init.py
testnexus/main.py
testnexus-0.1.2.dist-info/METADATA
testnexus-0.1.2.dist-info/WHEEL
testnexus-0.1.2.dist-info/entry_points.txt
testnexus-0.1.2.dist-info/top_level.txt
testnexus-0.1.2.dist-info/RECORD
