Metadata-Version: 2.4
Name: testnexus
Version: 0.1.2
Summary: sj测试
Requires-Python: >=3.13
Requires-Dist: mcp[cli]>=1.15.0
